circles_local_database_python/__init__.py
circles_local_database_python/connector.py
circles_local_database_python/cursor.py
circles_local_database_python/generic_crud.py
circles_local_database_python/utils.py
database_sql_local-0.0.111.dist-info/LICENSE
database_sql_local-0.0.111.dist-info/METADATA
database_sql_local-0.0.111.dist-info/WHEEL
database_sql_local-0.0.111.dist-info/top_level.txt
database_sql_local-0.0.111.dist-info/RECORD
