Metadata-Version: 2.1
Name: database-sql-local
Version: 0.0.111
Home-page: https://github.com/circles-zone/database-sql-local-python-package
Author: Circles
Author-email: info@circles.life
Classifier: Programming Language :: Python :: 3
Classifier: License :: Other/Proprietary License
Classifier: Operating System :: OS Independent
License-File: LICENSE
Requires-Dist: mysql-connector >=2.2.9
Requires-Dist: python-dotenv >=1.0.0
Requires-Dist: logger-local >=0.0.66
Requires-Dist: pytest >=7.4.0
Requires-Dist: PyMySQL >=1.0.2
Requires-Dist: database-infrastructure-local >=0.0.15
